{
	"version": "2.0",
	"name": "loop",
	"description": "",
	"points": 120000,
	"projection": "",
	"hierarchy": {
		"firstChunkSize": 2002, 
		"stepSize": 4, 
		"depth": 0
	},
	"offset": [-0.40417832136154175, -0.71818441152572632, -1.7501004934310913],
	"scale": [0.001, 0.001, 0.001],
	"spacing": 0.020710937500000002,
	"boundingBox": {
		"min": [-0.40417832136154175, -0.71818441152572632, -1.7501004934310913], 
		"max": [2.2468216786384585, 1.9328155884742739, 0.90089950656890894]
	},
	"encoding": "DEFAULT",
	"attributes": [
		{
			"name": "position",
			"description": "",
			"size": 12,
			"numElements": 3,
			"elementSize": 4,
			"type": "int32",
			"min": [-0.40417832136154175, -0.71818441152572632, -1.7501004934310913],
			"max": [0.59682167863845836, 0.48581558847427364, 0.90089950656890894],
			"scale": [1, 1, 1],
			"offset": [0, 0, 0]
		},{
			"name": "intensity",
			"description": "",
			"size": 2,
			"numElements": 1,
			"elementSize": 2,
			"type": "uint16",
			"min": [0],
			"max": [0],
			"scale": [1],
			"offset": [0]
		},{
			"name": "return number",
			"description": "",
			"size": 1,
			"numElements": 1,
			"elementSize": 1,
			"type": "uint8",
			"min": [0],
			"max": [0],
			"scale": [1],
			"offset": [0]
		},{
			"name": "number of returns",
			"description": "",
			"size": 1,
			"numElements": 1,
			"elementSize": 1,
			"type": "uint8",
			"min": [0],
			"max": [0],
			"scale": [1],
			"offset": [0]
		},{
			"name": "classification",
			"description": "",
			"size": 1,
			"numElements": 1,
			"elementSize": 1,
			"type": "uint8",
			"histogram": [120000, 0, 0, 0, 0, 0, 0, 0, 0, 0, 0, 0, 0, 0, 0, 0, 0, 0, 0, 0, 0, 0, 0, 0, 0, 0, 0, 0, 0, 0, 0, 0, 0, 0, 0, 0, 0, 0, 0, 0, 0, 0, 0, 0, 0, 0, 0, 0, 0, 0, 0, 0, 0, 0, 0, 0, 0, 0, 0, 0, 0, 0, 0, 0, 0, 0, 0, 0, 0, 0, 0, 0, 0, 0, 0, 0, 0, 0, 0, 0, 0, 0, 0, 0, 0, 0, 0, 0, 0, 0, 0, 0, 0, 0, 0, 0, 0, 0, 0, 0, 0, 0, 0, 0, 0, 0, 0, 0, 0, 0, 0, 0, 0, 0, 0, 0, 0, 0, 0, 0, 0, 0, 0, 0, 0, 0, 0, 0, 0, 0, 0, 0, 0, 0, 0, 0, 0, 0, 0, 0, 0, 0, 0, 0, 0, 0, 0, 0, 0, 0, 0, 0, 0, 0, 0, 0, 0, 0, 0, 0, 0, 0, 0, 0, 0, 0, 0, 0, 0, 0, 0, 0, 0, 0, 0, 0, 0, 0, 0, 0, 0, 0, 0, 0, 0, 0, 0, 0, 0, 0, 0, 0, 0, 0, 0, 0, 0, 0, 0, 0, 0, 0, 0, 0, 0, 0, 0, 0, 0, 0, 0, 0, 0, 0, 0, 0, 0, 0, 0, 0, 0, 0, 0, 0, 0, 0, 0, 0, 0, 0, 0, 0, 0, 0, 0, 0, 0, 0, 0, 0, 0, 0, 0, 0, 0, 0, 0, 0, 0, 0, 0, 0, 0, 0, 0, 0], 
			"min": [0],
			"max": [0],
			"scale": [1],
			"offset": [0]
		},{
			"name": "scan angle rank",
			"description": "",
			"size": 1,
			"numElements": 1,
			"elementSize": 1,
			"type": "uint8",
			"min": [0],
			"max": [0],
			"scale": [1],
			"offset": [0]
		},{
			"name": "user data",
			"description": "",
			"size": 1,
			"numElements": 1,
			"elementSize": 1,
			"type": "uint8",
			"min": [0],
			"max": [0],
			"scale": [1],
			"offset": [0]
		},{
			"name": "point source id",
			"description": "",
			"size": 2,
			"numElements": 1,
			"elementSize": 2,
			"type": "uint16",
			"min": [0],
			"max": [0],
			"scale": [1],
			"offset": [0]
		},{
			"name": "rgb",
			"description": "",
			"size": 6,
			"numElements": 3,
			"elementSize": 2,
			"type": "uint16",
			"min": [0, 0, 768],
			"max": [61440, 59136, 60160],
			"scale": [1, 1, 1],
			"offset": [0, 0, 0]
		}
	]
}
