{
	"version": "2.0",
	"name": "SYN_orbit",
	"description": "",
	"points": 320436,
	"projection": "",
	"hierarchy": {
		"firstChunkSize": 1738, 
		"stepSize": 4, 
		"depth": 5
	},
	"offset": [-0.93762004375457764, -0.70028591156005859, -19.972728729248047],
	"scale": [0.001, 0.001, 0.001],
	"spacing": 0.150640625,
	"boundingBox": {
		"min": [-0.93762004375457764, -0.70028591156005859, -19.972728729248047], 
		"max": [18.344379956245422, 18.581714088439941, -0.69072872924804685]
	},
	"encoding": "DEFAULT",
	"attributes": [
		{
			"name": "position",
			"description": "",
			"size": 12,
			"numElements": 3,
			"elementSize": 4,
			"type": "int32",
			"min": [-0.93762004375457764, -0.70028591156005859, -19.972728729248047],
			"max": [0.92737995624542235, 0.69271408843994142, -0.69072872924804685],
			"scale": [1, 1, 1],
			"offset": [0, 0, 0]
		},{
			"name": "intensity",
			"description": "",
			"size": 2,
			"numElements": 1,
			"elementSize": 2,
			"type": "uint16",
			"min": [0],
			"max": [0],
			"scale": [1],
			"offset": [0]
		},{
			"name": "return number",
			"description": "",
			"size": 1,
			"numElements": 1,
			"elementSize": 1,
			"type": "uint8",
			"min": [0],
			"max": [0],
			"scale": [1],
			"offset": [0]
		},{
			"name": "number of returns",
			"description": "",
			"size": 1,
			"numElements": 1,
			"elementSize": 1,
			"type": "uint8",
			"min": [0],
			"max": [0],
			"scale": [1],
			"offset": [0]
		},{
			"name": "classification",
			"description": "",
			"size": 1,
			"numElements": 1,
			"elementSize": 1,
			"type": "uint8",
			"histogram": [320436, 0, 0, 0, 0, 0, 0, 0, 0, 0, 0, 0, 0, 0, 0, 0, 0, 0, 0, 0, 0, 0, 0, 0, 0, 0, 0, 0, 0, 0, 0, 0, 0, 0, 0, 0, 0, 0, 0, 0, 0, 0, 0, 0, 0, 0, 0, 0, 0, 0, 0, 0, 0, 0, 0, 0, 0, 0, 0, 0, 0, 0, 0, 0, 0, 0, 0, 0, 0, 0, 0, 0, 0, 0, 0, 0, 0, 0, 0, 0, 0, 0, 0, 0, 0, 0, 0, 0, 0, 0, 0, 0, 0, 0, 0, 0, 0, 0, 0, 0, 0, 0, 0, 0, 0, 0, 0, 0, 0, 0, 0, 0, 0, 0, 0, 0, 0, 0, 0, 0, 0, 0, 0, 0, 0, 0, 0, 0, 0, 0, 0, 0, 0, 0, 0, 0, 0, 0, 0, 0, 0, 0, 0, 0, 0, 0, 0, 0, 0, 0, 0, 0, 0, 0, 0, 0, 0, 0, 0, 0, 0, 0, 0, 0, 0, 0, 0, 0, 0, 0, 0, 0, 0, 0, 0, 0, 0, 0, 0, 0, 0, 0, 0, 0, 0, 0, 0, 0, 0, 0, 0, 0, 0, 0, 0, 0, 0, 0, 0, 0, 0, 0, 0, 0, 0, 0, 0, 0, 0, 0, 0, 0, 0, 0, 0, 0, 0, 0, 0, 0, 0, 0, 0, 0, 0, 0, 0, 0, 0, 0, 0, 0, 0, 0, 0, 0, 0, 0, 0, 0, 0, 0, 0, 0, 0, 0, 0, 0, 0, 0, 0, 0, 0, 0, 0, 0], 
			"min": [0],
			"max": [0],
			"scale": [1],
			"offset": [0]
		},{
			"name": "scan angle rank",
			"description": "",
			"size": 1,
			"numElements": 1,
			"elementSize": 1,
			"type": "uint8",
			"min": [0],
			"max": [0],
			"scale": [1],
			"offset": [0]
		},{
			"name": "user data",
			"description": "",
			"size": 1,
			"numElements": 1,
			"elementSize": 1,
			"type": "uint8",
			"min": [0],
			"max": [0],
			"scale": [1],
			"offset": [0]
		},{
			"name": "point source id",
			"description": "",
			"size": 2,
			"numElements": 1,
			"elementSize": 2,
			"type": "uint16",
			"min": [0],
			"max": [0],
			"scale": [1],
			"offset": [0]
		},{
			"name": "rgb",
			"description": "",
			"size": 6,
			"numElements": 3,
			"elementSize": 2,
			"type": "uint16",
			"min": [2048, 2048, 8448],
			"max": [55296, 55296, 45312],
			"scale": [1, 1, 1],
			"offset": [0, 0, 0]
		}
	]
}
