{
	"version": "2.0",
	"name": "oxford",
	"description": "",
	"points": 120000,
	"projection": "",
	"hierarchy": {
		"firstChunkSize": 2310, 
		"stepSize": 4, 
		"depth": 0
	},
	"offset": [-2.1443791389465332, -0.4938066303730011, -3.4041898250579834],
	"scale": [0.001, 0.001, 0.001],
	"spacing": 0.044820312500000001,
	"boundingBox": {
		"min": [-2.1443791389465332, -0.4938066303730011, -3.4041898250579834], 
		"max": [3.5926208610534669, 5.243193369626999, 2.3328101749420167]
	},
	"encoding": "DEFAULT",
	"attributes": [
		{
			"name": "position",
			"description": "",
			"size": 12,
			"numElements": 3,
			"elementSize": 4,
			"type": "int32",
			"min": [-2.1443791389465332, -0.4938066303730011, -3.4041898250579834],
			"max": [1.9716208610534665, 1.8341933696269987, 2.3328101749420167],
			"scale": [1, 1, 1],
			"offset": [0, 0, 0]
		},{
			"name": "intensity",
			"description": "",
			"size": 2,
			"numElements": 1,
			"elementSize": 2,
			"type": "uint16",
			"min": [0],
			"max": [0],
			"scale": [1],
			"offset": [0]
		},{
			"name": "return number",
			"description": "",
			"size": 1,
			"numElements": 1,
			"elementSize": 1,
			"type": "uint8",
			"min": [0],
			"max": [0],
			"scale": [1],
			"offset": [0]
		},{
			"name": "number of returns",
			"description": "",
			"size": 1,
			"numElements": 1,
			"elementSize": 1,
			"type": "uint8",
			"min": [0],
			"max": [0],
			"scale": [1],
			"offset": [0]
		},{
			"name": "classification",
			"description": "",
			"size": 1,
			"numElements": 1,
			"elementSize": 1,
			"type": "uint8",
			"histogram": [120000, 0, 0, 0, 0, 0, 0, 0, 0, 0, 0, 0, 0, 0, 0, 0, 0, 0, 0, 0, 0, 0, 0, 0, 0, 0, 0, 0, 0, 0, 0, 0, 0, 0, 0, 0, 0, 0, 0, 0, 0, 0, 0, 0, 0, 0, 0, 0, 0, 0, 0, 0, 0, 0, 0, 0, 0, 0, 0, 0, 0, 0, 0, 0, 0, 0, 0, 0, 0, 0, 0, 0, 0, 0, 0, 0, 0, 0, 0, 0, 0, 0, 0, 0, 0, 0, 0, 0, 0, 0, 0, 0, 0, 0, 0, 0, 0, 0, 0, 0, 0, 0, 0, 0, 0, 0, 0, 0, 0, 0, 0, 0, 0, 0, 0, 0, 0, 0, 0, 0, 0, 0, 0, 0, 0, 0, 0, 0, 0, 0, 0, 0, 0, 0, 0, 0, 0, 0, 0, 0, 0, 0, 0, 0, 0, 0, 0, 0, 0, 0, 0, 0, 0, 0, 0, 0, 0, 0, 0, 0, 0, 0, 0, 0, 0, 0, 0, 0, 0, 0, 0, 0, 0, 0, 0, 0, 0, 0, 0, 0, 0, 0, 0, 0, 0, 0, 0, 0, 0, 0, 0, 0, 0, 0, 0, 0, 0, 0, 0, 0, 0, 0, 0, 0, 0, 0, 0, 0, 0, 0, 0, 0, 0, 0, 0, 0, 0, 0, 0, 0, 0, 0, 0, 0, 0, 0, 0, 0, 0, 0, 0, 0, 0, 0, 0, 0, 0, 0, 0, 0, 0, 0, 0, 0, 0, 0, 0, 0, 0, 0, 0, 0, 0, 0, 0, 0], 
			"min": [0],
			"max": [0],
			"scale": [1],
			"offset": [0]
		},{
			"name": "scan angle rank",
			"description": "",
			"size": 1,
			"numElements": 1,
			"elementSize": 1,
			"type": "uint8",
			"min": [0],
			"max": [0],
			"scale": [1],
			"offset": [0]
		},{
			"name": "user data",
			"description": "",
			"size": 1,
			"numElements": 1,
			"elementSize": 1,
			"type": "uint8",
			"min": [0],
			"max": [0],
			"scale": [1],
			"offset": [0]
		},{
			"name": "point source id",
			"description": "",
			"size": 2,
			"numElements": 1,
			"elementSize": 2,
			"type": "uint16",
			"min": [0],
			"max": [0],
			"scale": [1],
			"offset": [0]
		},{
			"name": "rgb",
			"description": "",
			"size": 6,
			"numElements": 3,
			"elementSize": 2,
			"type": "uint16",
			"min": [4352, 4352, 4352],
			"max": [65280, 65280, 65280],
			"scale": [1, 1, 1],
			"offset": [0, 0, 0]
		}
	]
}
